arlq/__init__.py
arlq/_version.py
arlq/arlq.py
arlq/compat_screen.py
arlq-1.3.0.dist-info/LICENSE
arlq-1.3.0.dist-info/METADATA
arlq-1.3.0.dist-info/WHEEL
arlq-1.3.0.dist-info/entry_points.txt
arlq-1.3.0.dist-info/top_level.txt
arlq-1.3.0.dist-info/RECORD
