Metadata-Version: 2.1
Name: arlq
Version: 1.3.0
Summary: ARQL, another rogue-like quest game.
Author-email: Toshihiro Kamiya <kamiya@mbj.nifty.com>
License: BSD 2-Clause License
Project-URL: Homepage, https://github.com/tos-kamiya/arlq
Classifier: Programming Language :: Python :: 3.8
Classifier: Programming Language :: Python :: 3.9
Classifier: Programming Language :: Python :: 3.10
Classifier: License :: OSI Approved :: BSD License
Classifier: Operating System :: MacOS :: MacOS X
Classifier: Operating System :: POSIX :: Linux
Classifier: Operating System :: Microsoft :: Windows
Requires-Python: >=3.8
License-File: LICENSE
Requires-Dist: windows-curses ; sys_platform == "win32"
